taco/__init__.py
taco_kit-0.0.0.dist-info/METADATA
taco_kit-0.0.0.dist-info/WHEEL
taco_kit-0.0.0.dist-info/top_level.txt
taco_kit-0.0.0.dist-info/RECORD
